aioviberbot/__init__.py
aioviberbot/version.py
aioviberbot/api/__init__.py
aioviberbot/api/api.py
aioviberbot/api/api_request_sender.py
aioviberbot/api/bot_configuration.py
aioviberbot/api/consts.py
aioviberbot/api/errors.py
aioviberbot/api/event_type.py
aioviberbot/api/message_sender.py
aioviberbot/api/user_profile.py
aioviberbot/api/messages/__init__.py
aioviberbot/api/messages/contact_message.py
aioviberbot/api/messages/file_message.py
aioviberbot/api/messages/keyboard_message.py
aioviberbot/api/messages/location_message.py
aioviberbot/api/messages/message.py
aioviberbot/api/messages/message_type.py
aioviberbot/api/messages/picture_message.py
aioviberbot/api/messages/rich_media_message.py
aioviberbot/api/messages/sticker_message.py
aioviberbot/api/messages/text_message.py
aioviberbot/api/messages/typed_message.py
aioviberbot/api/messages/url_message.py
aioviberbot/api/messages/video_message.py
aioviberbot/api/messages/data_types/__init__.py
aioviberbot/api/messages/data_types/contact.py
aioviberbot/api/messages/data_types/location.py
aioviberbot/api/viber_requests/__init__.py
aioviberbot/api/viber_requests/viber_conversation_started_request.py
aioviberbot/api/viber_requests/viber_delivered_request.py
aioviberbot/api/viber_requests/viber_failed_request.py
aioviberbot/api/viber_requests/viber_message_request.py
aioviberbot/api/viber_requests/viber_request.py
aioviberbot/api/viber_requests/viber_seen_request.py
aioviberbot/api/viber_requests/viber_subscribed_request.py
aioviberbot/api/viber_requests/viber_unsubscribed_request.py
aioviberbot-0.7.0.dist-info/LICENSE.md
aioviberbot-0.7.0.dist-info/METADATA
aioviberbot-0.7.0.dist-info/WHEEL
aioviberbot-0.7.0.dist-info/top_level.txt
aioviberbot-0.7.0.dist-info/RECORD
